LICENSE
README.md
setup.py
data_wizard/__init__.py
data_wizard/admin.py
data_wizard/apps.py
data_wizard/fields.py
data_wizard/idmap.py
data_wizard/loaders.py
data_wizard/models.py
data_wizard/registry.py
data_wizard/rest.py
data_wizard/serializers.py
data_wizard/settings.py
data_wizard/signals.py
data_wizard/tasks.py
data_wizard/test.py
data_wizard/urls.py
data_wizard/views.py
data_wizard/backends/__init__.py
data_wizard/backends/base.py
data_wizard/backends/celery.py
data_wizard/backends/immediate.py
data_wizard/backends/threading.py
data_wizard/management/__init__.py
data_wizard/management/commands/__init__.py
data_wizard/management/commands/runwizard.py
data_wizard/migrations/0001_initial.py
data_wizard/migrations/0002_auto_20190306_2022.py
data_wizard/migrations/0003_alter_run_options.py
data_wizard/migrations/__init__.py
data_wizard/sources/__init__.py
data_wizard/sources/admin.py
data_wizard/sources/apps.py
data_wizard/sources/models.py
data_wizard/sources/rest.py
data_wizard/sources/wizard.py
data_wizard/sources/migrations/0001_initial.py
data_wizard/sources/migrations/0002_source_user.py
data_wizard/sources/migrations/__init__.py
data_wizard/static/app/js/wizard.js
data_wizard/static/app/js/wizard.js.map
data_wizard/static/data_wizard/css/base.css
data_wizard/static/data_wizard/js/progress-element.js
data_wizard/templates/data_wizard/back.html
data_wizard/templates/data_wizard/base_site.html
data_wizard/templates/data_wizard/continue.html
data_wizard/templates/data_wizard/progress.html
data_wizard/templates/data_wizard/run_auto.html
data_wizard/templates/data_wizard/run_columns.html
data_wizard/templates/data_wizard/run_data.html
data_wizard/templates/data_wizard/run_detail.html
data_wizard/templates/data_wizard/run_ids.html
data_wizard/templates/data_wizard/run_list.html
data_wizard/templates/data_wizard/run_records.html
data_wizard/templates/data_wizard/run_serializers.html
data_wizard_edx_copy.egg-info/PKG-INFO
data_wizard_edx_copy.egg-info/SOURCES.txt
data_wizard_edx_copy.egg-info/dependency_links.txt
data_wizard_edx_copy.egg-info/requires.txt
data_wizard_edx_copy.egg-info/top_level.txt