Metadata-Version: 2.1
Name: data-wizard-edx-copy
Version: 1.3.1
Summary: Interactive web-based wizard for importing structured data into Django models.
Home-page: https://github.com/wq/django-data-wizard
Author: S. Andrew Sheppard
Author-email: andrew@wq.io
License: MIT
Platform: UNKNOWN
Classifier: Development Status :: 5 - Production/Stable
Classifier: Environment :: Web Environment
Classifier: License :: OSI Approved :: MIT License
Classifier: Natural Language :: English
Classifier: Programming Language :: JavaScript
Classifier: Programming Language :: Python :: 3
Classifier: Programming Language :: Python :: 3.6
Classifier: Programming Language :: Python :: 3.7
Classifier: Programming Language :: Python :: 3.8
Classifier: Programming Language :: Python :: 3.9
Classifier: Programming Language :: Python :: 3.10
Classifier: Framework :: Django
Classifier: Framework :: Django :: 2.2
Classifier: Framework :: Django :: 3.0
Classifier: Framework :: Django :: 3.1
Classifier: Framework :: Django :: 3.2
Classifier: Framework :: Django :: 4.0
Classifier: Topic :: Scientific/Engineering :: GIS
Classifier: Topic :: Database :: Database Engines/Servers
License-File: LICENSE
